ringelcoord/__init__.py
ringelcoord-0.0.3.dist-info/LICENSE
ringelcoord-0.0.3.dist-info/METADATA
ringelcoord-0.0.3.dist-info/WHEEL
ringelcoord-0.0.3.dist-info/top_level.txt
ringelcoord-0.0.3.dist-info/RECORD
