Metadata-Version: 2.1
Name: ringelcoord
Version: 0.0.3
Summary: A ringelcoord bot API
Author-email: John Janzen <rc-dev@johnjanzen.me>
Classifier: Programming Language :: Python :: 3
Classifier: License :: OSI Approved :: GNU General Public License (GPL)
Classifier: Operating System :: OS Independent
Requires-Python: >=3.7
License-File: LICENSE
Requires-Dist: websockets (~=11.0)
